{
  "$schema": "https://schema.management.azure.com/schemas/2018-05-01/subscriptionDeploymentTemplate.json#",
  "contentVersion": "1.0.0.0",
  "metadata": {
    "_generator": {
      "name": "bicep",
      "version": "0.43.8.12551",
      "templateHash": "4243826522129215585"
    }
  },
  "parameters": {
    "environmentName": {
      "type": "string",
      "metadata": {
        "description": "Environment name (dev, staging, prod)"
      }
    },
    "location": {
      "type": "string",
      "metadata": {
        "description": "Primary Azure region for all resources"
      }
    }
  },
  "variables": {
    "resourceToken": "[toLower(uniqueString(subscription().id, parameters('environmentName'), parameters('location')))]"
  },
  "resources": [
    {
      "type": "Microsoft.Resources/resourceGroups",
      "apiVersion": "2021-04-01",
      "name": "[format('rg-chatbot-{0}', parameters('environmentName'))]",
      "location": "[parameters('location')]",
      "tags": {
        "azd-env-name": "[parameters('environmentName')]",
        "project": "chatbot-azure"
      }
    },
    {
      "type": "Microsoft.Resources/deployments",
      "apiVersion": "2025-04-01",
      "name": "storage",
      "resourceGroup": "[format('rg-chatbot-{0}', parameters('environmentName'))]",
      "properties": {
        "expressionEvaluationOptions": {
          "scope": "inner"
        },
        "mode": "Incremental",
        "parameters": {
          "location": {
            "value": "[parameters('location')]"
          },
          "environmentName": {
            "value": "[parameters('environmentName')]"
          },
          "resourceToken": {
            "value": "[variables('resourceToken')]"
          }
        },
        "template": {
          "$schema": "https://schema.management.azure.com/schemas/2019-04-01/deploymentTemplate.json#",
          "contentVersion": "1.0.0.0",
          "metadata": {
            "_generator": {
              "name": "bicep",
              "version": "0.43.8.12551",
              "templateHash": "7926182246146233850"
            }
          },
          "parameters": {
            "location": {
              "type": "string"
            },
            "environmentName": {
              "type": "string"
            },
            "resourceToken": {
              "type": "string"
            }
          },
          "resources": [
            {
              "type": "Microsoft.Storage/storageAccounts",
              "apiVersion": "2023-01-01",
              "name": "[format('stchatbot{0}', parameters('resourceToken'))]",
              "location": "[parameters('location')]",
              "sku": {
                "name": "Standard_LRS"
              },
              "kind": "StorageV2",
              "tags": {
                "azd-env-name": "[parameters('environmentName')]"
              },
              "properties": {
                "minimumTlsVersion": "TLS1_2",
                "supportsHttpsTrafficOnly": true,
                "allowBlobPublicAccess": false
              }
            },
            {
              "type": "Microsoft.Storage/storageAccounts/blobServices",
              "apiVersion": "2023-01-01",
              "name": "[format('{0}/{1}', format('stchatbot{0}', parameters('resourceToken')), 'default')]",
              "dependsOn": [
                "[resourceId('Microsoft.Storage/storageAccounts', format('stchatbot{0}', parameters('resourceToken')))]"
              ]
            },
            {
              "type": "Microsoft.Storage/storageAccounts/blobServices/containers",
              "apiVersion": "2023-01-01",
              "name": "[format('{0}/{1}/{2}', format('stchatbot{0}', parameters('resourceToken')), 'default', 'uploads')]",
              "properties": {
                "publicAccess": "None"
              },
              "dependsOn": [
                "[resourceId('Microsoft.Storage/storageAccounts/blobServices', format('stchatbot{0}', parameters('resourceToken')), 'default')]"
              ]
            },
            {
              "type": "Microsoft.Storage/storageAccounts/blobServices/containers",
              "apiVersion": "2023-01-01",
              "name": "[format('{0}/{1}/{2}', format('stchatbot{0}', parameters('resourceToken')), 'default', 'staging')]",
              "properties": {
                "publicAccess": "None"
              },
              "dependsOn": [
                "[resourceId('Microsoft.Storage/storageAccounts/blobServices', format('stchatbot{0}', parameters('resourceToken')), 'default')]"
              ]
            },
            {
              "type": "Microsoft.Storage/storageAccounts/blobServices/containers",
              "apiVersion": "2023-01-01",
              "name": "[format('{0}/{1}/{2}', format('stchatbot{0}', parameters('resourceToken')), 'default', 'rag-temp')]",
              "properties": {
                "publicAccess": "None"
              },
              "dependsOn": [
                "[resourceId('Microsoft.Storage/storageAccounts/blobServices', format('stchatbot{0}', parameters('resourceToken')), 'default')]"
              ]
            },
            {
              "type": "Microsoft.Storage/storageAccounts/managementPolicies",
              "apiVersion": "2023-01-01",
              "name": "[format('{0}/{1}', format('stchatbot{0}', parameters('resourceToken')), 'default')]",
              "properties": {
                "policy": {
                  "rules": [
                    {
                      "name": "expire-staging-uploads",
                      "type": "Lifecycle",
                      "definition": {
                        "actions": {
                          "baseBlob": {
                            "delete": {
                              "daysAfterModificationGreaterThan": 7
                            }
                          }
                        },
                        "filters": {
                          "blobTypes": [
                            "blockBlob"
                          ],
                          "prefixMatch": [
                            "staging/",
                            "rag-temp/"
                          ]
                        }
                      }
                    }
                  ]
                }
              },
              "dependsOn": [
                "[resourceId('Microsoft.Storage/storageAccounts', format('stchatbot{0}', parameters('resourceToken')))]"
              ]
            }
          ],
          "outputs": {
            "storageAccountName": {
              "type": "string",
              "value": "[format('stchatbot{0}', parameters('resourceToken'))]"
            },
            "storageAccountId": {
              "type": "string",
              "value": "[resourceId('Microsoft.Storage/storageAccounts', format('stchatbot{0}', parameters('resourceToken')))]"
            }
          }
        }
      },
      "dependsOn": [
        "[subscriptionResourceId('Microsoft.Resources/resourceGroups', format('rg-chatbot-{0}', parameters('environmentName')))]"
      ]
    },
    {
      "type": "Microsoft.Resources/deployments",
      "apiVersion": "2025-04-01",
      "name": "cosmos",
      "resourceGroup": "[format('rg-chatbot-{0}', parameters('environmentName'))]",
      "properties": {
        "expressionEvaluationOptions": {
          "scope": "inner"
        },
        "mode": "Incremental",
        "parameters": {
          "location": {
            "value": "[parameters('location')]"
          },
          "environmentName": {
            "value": "[parameters('environmentName')]"
          }
        },
        "template": {
          "$schema": "https://schema.management.azure.com/schemas/2019-04-01/deploymentTemplate.json#",
          "contentVersion": "1.0.0.0",
          "metadata": {
            "_generator": {
              "name": "bicep",
              "version": "0.43.8.12551",
              "templateHash": "8810771708603633650"
            }
          },
          "parameters": {
            "location": {
              "type": "string"
            },
            "environmentName": {
              "type": "string"
            }
          },
          "resources": [
            {
              "type": "Microsoft.DocumentDB/databaseAccounts",
              "apiVersion": "2023-11-15",
              "name": "[format('cosmos-chatbot-{0}', parameters('environmentName'))]",
              "location": "[parameters('location')]",
              "kind": "GlobalDocumentDB",
              "properties": {
                "enableFreeTier": true,
                "databaseAccountOfferType": "Standard",
                "capabilities": [
                  {
                    "name": "EnableNoSQLVectorSearch"
                  }
                ],
                "locations": [
                  {
                    "locationName": "[parameters('location')]",
                    "failoverPriority": 0
                  }
                ],
                "consistencyPolicy": {
                  "defaultConsistencyLevel": "Session"
                }
              }
            },
            {
              "type": "Microsoft.DocumentDB/databaseAccounts/sqlDatabases",
              "apiVersion": "2023-11-15",
              "name": "[format('{0}/{1}', format('cosmos-chatbot-{0}', parameters('environmentName')), 'chatbot')]",
              "properties": {
                "resource": {
                  "id": "chatbot"
                }
              },
              "dependsOn": [
                "[resourceId('Microsoft.DocumentDB/databaseAccounts', format('cosmos-chatbot-{0}', parameters('environmentName')))]"
              ]
            },
            {
              "type": "Microsoft.DocumentDB/databaseAccounts/sqlDatabases/containers",
              "apiVersion": "2023-11-15",
              "name": "[format('{0}/{1}/{2}', format('cosmos-chatbot-{0}', parameters('environmentName')), 'chatbot', 'conversations')]",
              "properties": {
                "resource": {
                  "id": "conversations",
                  "partitionKey": {
                    "paths": [
                      "/conversationId"
                    ],
                    "kind": "Hash"
                  },
                  "defaultTtl": -1,
                  "indexingPolicy": {
                    "indexingMode": "consistent",
                    "includedPaths": [
                      {
                        "path": "/*"
                      }
                    ],
                    "excludedPaths": [
                      {
                        "path": "/_etag/?"
                      }
                    ]
                  }
                },
                "options": {
                  "throughput": 400
                }
              },
              "dependsOn": [
                "[resourceId('Microsoft.DocumentDB/databaseAccounts/sqlDatabases', format('cosmos-chatbot-{0}', parameters('environmentName')), 'chatbot')]"
              ]
            },
            {
              "type": "Microsoft.DocumentDB/databaseAccounts/sqlDatabases/containers",
              "apiVersion": "2023-11-15",
              "name": "[format('{0}/{1}/{2}', format('cosmos-chatbot-{0}', parameters('environmentName')), 'chatbot', 'vectors')]",
              "properties": {
                "resource": {
                  "id": "vectors",
                  "partitionKey": {
                    "paths": [
                      "/userId"
                    ],
                    "kind": "Hash"
                  },
                  "indexingPolicy": {
                    "indexingMode": "consistent",
                    "includedPaths": [
                      {
                        "path": "/*"
                      }
                    ],
                    "excludedPaths": [
                      {
                        "path": "/embedding/*"
                      },
                      {
                        "path": "/_etag/?"
                      }
                    ],
                    "vectorIndexes": [
                      {
                        "path": "/embedding",
                        "type": "quantizedFlat"
                      }
                    ]
                  },
                  "vectorEmbeddingPolicy": {
                    "vectorEmbeddings": [
                      {
                        "path": "/embedding",
                        "dataType": "float32",
                        "dimensions": 768,
                        "distanceFunction": "cosine"
                      }
                    ]
                  }
                },
                "options": {
                  "throughput": 400
                }
              },
              "dependsOn": [
                "[resourceId('Microsoft.DocumentDB/databaseAccounts/sqlDatabases', format('cosmos-chatbot-{0}', parameters('environmentName')), 'chatbot')]"
              ]
            }
          ],
          "outputs": {
            "cosmosAccountName": {
              "type": "string",
              "value": "[format('cosmos-chatbot-{0}', parameters('environmentName'))]"
            },
            "cosmosEndpoint": {
              "type": "string",
              "value": "[reference(resourceId('Microsoft.DocumentDB/databaseAccounts', format('cosmos-chatbot-{0}', parameters('environmentName'))), '2023-11-15').documentEndpoint]"
            },
            "cosmosDatabaseName": {
              "type": "string",
              "value": "chatbot"
            }
          }
        }
      },
      "dependsOn": [
        "[subscriptionResourceId('Microsoft.Resources/resourceGroups', format('rg-chatbot-{0}', parameters('environmentName')))]"
      ]
    }
  ],
  "outputs": {
    "AZURE_STORAGE_ACCOUNT_NAME": {
      "type": "string",
      "value": "[reference(extensionResourceId(format('/subscriptions/{0}/resourceGroups/{1}', subscription().subscriptionId, format('rg-chatbot-{0}', parameters('environmentName'))), 'Microsoft.Resources/deployments', 'storage'), '2025-04-01').outputs.storageAccountName.value]"
    },
    "COSMOS_ENDPOINT": {
      "type": "string",
      "value": "[reference(extensionResourceId(format('/subscriptions/{0}/resourceGroups/{1}', subscription().subscriptionId, format('rg-chatbot-{0}', parameters('environmentName'))), 'Microsoft.Resources/deployments', 'cosmos'), '2025-04-01').outputs.cosmosEndpoint.value]"
    },
    "COSMOS_DATABASE_NAME": {
      "type": "string",
      "value": "[reference(extensionResourceId(format('/subscriptions/{0}/resourceGroups/{1}', subscription().subscriptionId, format('rg-chatbot-{0}', parameters('environmentName'))), 'Microsoft.Resources/deployments', 'cosmos'), '2025-04-01').outputs.cosmosDatabaseName.value]"
    }
  }
}